<root><thread><filename>scholtes-d_outbox_personal_5.txt</filename><name>
</name><id>EPS001</id><email order="1"><date>Thu, 3 Jan 2002 20:29:27 -0800 (PST)
</date><from>sf@smith-electric.com
</from><to>dscholt@ect.enron.com
</to><subject>
</subject><text><sentence id="EPS001_001">Hey,  Does your email still work.
</sentence><sentence id="EPS001_002">I was wondering if you had a private email that would be appropriate for non business related correspondence??  Just curious.
</sentence><sentence id="EPS001_003">Still would like to find a way to keep in touch better, the messenger thing is ok, but its hard at times with work and all.
</sentence><sentence id="EPS001_004">At least with email we can say alittle more and at least have some uninterrupted time to "talk".
</sentence><sentence id="EPS001_005">Speaking of talking?.is there any time that is good to call?
</sentence><sentence id="EPS001_006">I would like to hear your voice once in a while!
</sentence><sentence id="EPS001_007">J 
</sentence><signature>Steve</signature></text></email></thread></root>
