<root><thread><filename>jones-t_sent_218.txt</filename><name>Online Trading
</name><id>ECS081</id><email order="1"><date>Wed, 25 Aug 1999 03:35:00 -0700 (PDT)
</date><from>tana.jones@enron.com
</from><to>nick.mooney@enron.com
</to><subject>Online Trading
</subject><text><sentence id="ECS081_001">Michael Corbally just wanted me to confirm the following with you.
</sentence><sentence id="ECS081_002">Per the list of Datasources you sent me, for France we've got Meteo France listed at the Paris address.
</sentence><sentence id="ECS081_003">We had a confirm earlier this year using Meteo France where we used their Toulouse address.
</sentence><sentence id="ECS081_004">I just wanted to confirm that the address we want as the standard address will be the Meteo France out of Paris, not Toulouse.
</sentence><sentence id="ECS081_005">If you'll just confirm that for me.
</sentence><signature></signature></text></email></thread></root>
